kdrob/__init__.py
kdrob/calculator.py
kdrob/robotics.py
kdrob-0.5.dist-info/METADATA
kdrob-0.5.dist-info/WHEEL
kdrob-0.5.dist-info/top_level.txt
kdrob-0.5.dist-info/RECORD
