Metadata-Version: 2.4
Name: kdrob
Version: 0.5
Summary: Simple robotics utility library
Author: Kalpesh
Dynamic: author
Dynamic: summary
